.DS_Store
PW-explorer/Preprocessing.py
PW-explorer/__init__.py
PW-explorer/complexity_calc.py
PW-explorer/dist_calc.py
PW-explorer/export.py
PW-explorer/load_worlds.py
PW-explorer/pwe_helper.py
PW-explorer/pwe_query.py
PW-explorer/run_clingo.py
PW-explorer/sql_funcs.py
PW-explorer/sql_query.py
PW-explorer/visualize.py
PW-explorer/Custom_Complexity_Analysis_Functions/__init__.py
PW-explorer/Custom_Distance_Functions/__init__.py
PW-explorer/Custom_Distance_Functions/colorability_dist.py
PW-explorer/Custom_Distance_Functions/dummy_dist_func.py
PW-explorer/Custom_Distance_Functions/pwe_helper.py
PW-explorer/Custom_Visualization_Functions/__init__.py
PW-explorer/Custom_Visualization_Functions/euler_visualization.py
PW-explorer/Custom_Visualization_Functions/euler_visualization_nxpd.py
PW-explorer/Custom_Visualization_Functions/four_colorability_visualization.py
PW-explorer/Custom_Visualization_Functions/pwe_helper.py
PW-explorer/Custom_Visualization_Functions/test_vis.py
PW-explorer/Input_Parsers/__init__.py
PW-explorer/Input_Parsers/Clingo_Parser/__init__.py
PW-explorer/Input_Parsers/Clingo_Parser/clingo_parser.py
PW-explorer/Input_Parsers/Clingo_Parser/pwe_helper.py
PW-explorer/Input_Parsers/Clingo_Parser/Antlr_Files/ClingoLexer.py
PW-explorer/Input_Parsers/Clingo_Parser/Antlr_Files/ClingoListener.py
PW-explorer/Input_Parsers/Clingo_Parser/Antlr_Files/ClingoParser.py
PW-explorer/Input_Parsers/Clingo_Parser/Antlr_Files/__init__.py
PW-explorer/Input_Parsers/DLV_Parser/__init__.py
PW_explorer/Preprocessing.py
PW_explorer/__init__.py
PW_explorer/complexity_calc.py
PW_explorer/dist_calc.py
PW_explorer/export.py
PW_explorer/helper.py
PW_explorer/load_worlds.py
PW_explorer/meta_data_parser.py
PW_explorer/nb_helper.py
PW_explorer/pw_feature_calc.py
PW_explorer/pwe_helper.py
PW_explorer/pwe_nb_extension.py
PW_explorer/pwe_nb_helper.py
PW_explorer/pwe_query.py
PW_explorer/query.py
PW_explorer/run_clingo.py
PW_explorer/run_dlv.py
PW_explorer/sql_funcs.py
PW_explorer/sql_query.py
PW_explorer-0.0.25.dist-info/LICENSE
PW_explorer-0.0.25.dist-info/METADATA
PW_explorer-0.0.25.dist-info/WHEEL
PW_explorer-0.0.25.dist-info/top_level.txt
PW_explorer-0.0.25.dist-info/RECORD
