Metadata-Version: 2.1
Name: PW-explorer
Version: 0.0.25
Summary: An Extensible Possible World Explorer for Answer Set Programming
Home-page: https://github.com/idaks/PW-explorer
Author: Sahil Gupta
Author-email: 
License: UNKNOWN
Platform: UNKNOWN
Classifier: Programming Language :: Python :: 3
Classifier: License :: OSI Approved :: Apache Software License
Classifier: Operating System :: OS Independent
Requires-Dist: antlr4-python3-runtime (>=4.7.1)
Requires-Dist: decorator (>=4.1.2)
Requires-Dist: future (>=0.16.0)
Requires-Dist: matplotlib (>=3.0.3)
Requires-Dist: networkx (>=2.1)
Requires-Dist: numpy (>=1.14.2)
Requires-Dist: nxpd (>=0.2.0)
Requires-Dist: pandas (>=0.20.3)
Requires-Dist: pyparsing (>=2.2.0)
Requires-Dist: scikit-learn (>=0.19.0)
Requires-Dist: scipy (>=1.1.0)
Requires-Dist: seaborn (>=0.9.0)
Requires-Dist: sklearn (>=0.0)
Requires-Dist: subprocess32 (>=3.2.7)
